stv_utils/__init__.py
stv_utils/color.py
stv_utils/output.py
stv_utils/output_control.py
stv_utils/system_utils.py
stv_utils-0.0.8.dist-info/METADATA
stv_utils-0.0.8.dist-info/WHEEL
stv_utils-0.0.8.dist-info/top_level.txt
stv_utils-0.0.8.dist-info/RECORD
