Metadata-Version: 2.4
Name: stv_utils
Version: 0.0.8
Summary: Some commonly used tool functions.
Author-email: "星灿长风v(StarWindv)" <starwindv.stv@gmail.com>
License: MIT
Project-URL: Homepage, https://github.com/StarWindv/
Classifier: Programming Language :: Python :: 3
Requires-Python: >=3.10
